CHANGELOG.md
LICENSE
go_util/__init__.py
go_util/__main__.py
go_util/bookmarks.py
go_util/cli.py
go_util/consent.py
go_util-1.2.0.dist-info/LICENSE
go_util-1.2.0.dist-info/METADATA
go_util-1.2.0.dist-info/WHEEL
go_util-1.2.0.dist-info/entry_points.txt
go_util-1.2.0.dist-info/RECORD
