Metadata-Version: 2.1
Name: go_util
Version: 1.2.0
Summary: A CLI bookmark manager
Home-page: https://github.com/aidenm2244/go-util
License: End User License Agreement (EULA)
Keywords: CLI,bookmark,manager
Author: Aiden McCormack
Author-email: aidenm2244@proton.me
Requires-Python: >=3.9
Classifier: License :: Other/Proprietary License
Classifier: Operating System :: OS Independent
Classifier: Programming Language :: Python :: 3
Classifier: Programming Language :: Python :: 3.9
Classifier: Programming Language :: Python :: 3.10
Classifier: Programming Language :: Python :: 3.11
Classifier: Programming Language :: Python :: 3.12
Requires-Dist: appdirs (>=1.4.4,<2.0.0)
Requires-Dist: click (>=8.1.7,<9.0.0)
